knowyourdata/__init__.py
knowyourdata/kyd.py
knowyourdata/kyd_html_display_template.py
knowyourdata-0.1.0a3.dist-info/DESCRIPTION.rst
knowyourdata-0.1.0a3.dist-info/METADATA
knowyourdata-0.1.0a3.dist-info/RECORD
knowyourdata-0.1.0a3.dist-info/WHEEL
knowyourdata-0.1.0a3.dist-info/metadata.json
knowyourdata-0.1.0a3.dist-info/top_level.txt
