Metadata-Version: 2.0
Name: knowyourdata
Version: 0.1.0a3
Summary: A package to display basic info about your data
Home-page: https://github.com/mubdi/knowyourdata
Author: Mubdi Rahman
Author-email: mubdirahman@yahoo.com
License: UNKNOWN
Project-URL: Documentation, http://knowyourdata.readthedocs.io/
Keywords: know your data description
Platform: UNKNOWN
Classifier: Development Status :: 3 - Alpha
Classifier: Intended Audience :: Science/Research
Classifier: Topic :: Scientific/Engineering :: Information Analysis
Classifier: License :: OSI Approved :: Apache Software License
Classifier: Programming Language :: Python :: 2
Classifier: Programming Language :: Python :: 2.7
Classifier: Programming Language :: Python :: 3
Classifier: Programming Language :: Python :: 3.4
Classifier: Programming Language :: Python :: 3.5
Classifier: Programming Language :: Python :: 3.6
Classifier: Programming Language :: Python :: 3.7
Requires-Dist: ipython
Requires-Dist: numpy
Provides-Extra: dev
Requires-Dist: check-manifest; extra == 'dev'
Provides-Extra: test
Requires-Dist: coverage; extra == 'test'
